jhlogger/__init__.py
jhlogger/logger.py
jhlogger-1.0.1.dist-info/licenses/LICENSE
jhlogger-1.0.1.dist-info/METADATA
jhlogger-1.0.1.dist-info/WHEEL
jhlogger-1.0.1.dist-info/top_level.txt
jhlogger-1.0.1.dist-info/RECORD
