Metadata-Version: 2.4
Name: jhlogger
Version: 1.0.1
Summary: A feature-rich, configurable logging module with structured JSON output
Home-page: https://github.com/Jacaranda-Health/jhlogger
Author: JH Dev
Author-email: JH Dev <dev@jacarandahealth.org>
License: MIT
Project-URL: Homepage, https://github.com/Jacaranda-Health/jhlogger
Project-URL: Bug Tracker, https://github.com/Jacaranda-Health/jhlogger/issues
Project-URL: Documentation, https://github.com/Jacaranda-Health/jhlogger/blob/main/README.md
Project-URL: Source Code, https://github.com/Jacaranda-Health/jhlogger
Keywords: logging,json,structured,cloudwatch,sentry,configurable,traceback,debug,monitoring
Classifier: Development Status :: 5 - Production/Stable
Classifier: Intended Audience :: Developers
Classifier: Topic :: Software Development :: Libraries :: Python Modules
Classifier: Topic :: System :: Logging
Classifier: License :: OSI Approved :: MIT License
Classifier: Programming Language :: Python :: 3
Classifier: Programming Language :: Python :: 3.8
Classifier: Programming Language :: Python :: 3.9
Classifier: Programming Language :: Python :: 3.10
Classifier: Programming Language :: Python :: 3.11
Classifier: Programming Language :: Python :: 3.12
Classifier: Operating System :: OS Independent
Requires-Python: >=3.8
License-File: LICENSE
Requires-Dist: structlog>=23.0.0
Requires-Dist: watchtower>=3.0.0
Requires-Dist: sentry-sdk>=1.0.0
Provides-Extra: dev
Requires-Dist: black>=24.8.0; extra == "dev"
Requires-Dist: flake8>=5.0.4; extra == "dev"
Requires-Dist: flake8-simplify>=0.22.0; extra == "dev"
Requires-Dist: isort>=5.13.2; extra == "dev"
Requires-Dist: pre-commit>=3.5.0; extra == "dev"
Requires-Dist: pytest>=8.3.5; extra == "dev"
Requires-Dist: pytest-cov>=4.0.0; extra == "dev"
Requires-Dist: mypy>=1.14.1; extra == "dev"
Provides-Extra: docs
Requires-Dist: sphinx>=5.0.0; extra == "docs"
Requires-Dist: sphinx-rtd-theme>=1.0.0; extra == "docs"
Dynamic: author
Dynamic: home-page
Dynamic: license-file
Dynamic: requires-python
